{
  "meta": { "adventureId": "food-truck", "studentId": "ingrid-7", "gradeBand": "1", "worldview": "christian", "faithLevel": 2 },
  "title": "Food Truck Challenge",
  "intro": "Du og dine venner finder en gammel varevogn. Kan den blive til en lille madbod til byens marked?",
  "images": {
    "coverPrompt": "cinematic dreamy soft light, diverse kids age 6-8, retro van becoming food truck, golden hour, hopeful",
    "scenePrompts": [
      "kids sketching colorful menus on tablets, stickers, simple icons",
      "market day with friendly crowd, joyful atmosphere"
    ]
  },
  "faithBlock": {
    "prayer": "Gud, hjælp os være venlige og dele med andre. Amen.",
    "scripture": ""Elsk din næste som dig selv." (Matt 22:39)"
  },
  "tasks": [
    { "subject": "nativeLanguage",  "title": "Navngiv madboden", "body": "Vælg et navn og skriv én sætning om, hvad I sælger.", "checks": ["1 kort sætning"], "estMinutes": 5 },
    { "subject": "mathematics",     "title": "Tæl ingredienser", "body": "Tæl 10 tomater og 5 boller: Hvor mange i alt?", "checks": ["rigtigt antal"], "estMinutes": 5 },
    { "subject": "languageLab",     "title": "2 ord på engelsk", "body": "Lær 'bread' og 'cheese'. Sig og skriv dem.", "checks": ["2 ord skrevet"], "estMinutes": 5 },
    { "subject": "science",         "title": "Hold maden kold", "body": "Sæt ✓ ved ting der skal i køleskab.", "checks": ["korrekte ✓"], "estMinutes": 5 },
    { "subject": "historyReligion", "title": "Dele et måltid",  "body": "Se billede af fællesspisning. Fortæl 1 ting man deler.", "checks": ["1 ting nævnt"], "estMinutes": 5 },
    { "subject": "geography",       "title": "Hvor er markedet?", "body": "Peg på kortet hvor byen er.", "checks": ["by markeret"], "estMinutes": 5 },
    { "subject": "computerTech",    "title": "Lav et ikon",      "body": "Vælg et emoji-ikon til jeres menu.", "checks": ["ikon valgt"], "estMinutes": 5 },
    { "subject": "creativeArts",    "title": "Farvelæg menu",    "body": "Farvelæg 3 retter på tabletten.", "checks": ["3 farver brugt"], "estMinutes": 5 },
    { "subject": "musicDiscovery",  "title": "Markedssang",      "body": "Lyt til 30 sek. musik og klap takten.", "checks": ["takten klappet"], "estMinutes": 5 },
    { "subject": "physicalEd",      "title": "Leveringsleg",     "body": "Rejs dig og gå 1 runde i rummet som 'levering'.", "checks": ["runde gået"], "estMinutes": 3 },
    { "subject": "mentalWellness",  "title": "Vennekort",        "body": "Sig 1 venlig sætning til en klassekammerat.", "checks": ["1 sætning"], "estMinutes": 3 },
    { "subject": "lifeEssentials",  "title": "Rengør hænder",    "body": "Se 20-sek. håndvaskvideo og øv bevægelserne.", "checks": ["video set"], "estMinutes": 4 }
  ],
  "progressTags": ["ELA.K.W.1","MATH.1.OA","SCI.K-1.Health","SEL.K"]
}